list_of_links/__init__.py
list_of_links/frontend/build/asset-manifest.json
list_of_links/frontend/build/bootstrap.min.css
list_of_links/frontend/build/index.html
list_of_links/frontend/build/static/css/main.4459e327.css
list_of_links/frontend/build/static/css/main.4459e327.css.map
list_of_links/frontend/build/static/js/main.f2ead37a.js
list_of_links/frontend/build/static/js/main.f2ead37a.js.LICENSE.txt
list_of_links/frontend/build/static/js/main.f2ead37a.js.map
streamlit_list_of_links-0.1.10.dist-info/licenses/LICENSE
streamlit_list_of_links-0.1.10.dist-info/METADATA
streamlit_list_of_links-0.1.10.dist-info/WHEEL
streamlit_list_of_links-0.1.10.dist-info/top_level.txt
streamlit_list_of_links-0.1.10.dist-info/RECORD
