Metadata-Version: 2.4
Name: streamlit-list-of-links
Version: 0.1.10
Summary: Streamlit component that renders a list of links
Home-page: 
Author: Marc Argent
Author-email: margent@gmail.com
Requires-Python: >=3.10
License-File: LICENSE
Requires-Dist: streamlit>=1.43.0
Provides-Extra: tests
Requires-Dist: wheel; extra == "tests"
Requires-Dist: pytest==7.4.0; extra == "tests"
Requires-Dist: playwright==1.48.0; extra == "tests"
Requires-Dist: requests==2.31.0; extra == "tests"
Requires-Dist: pytest-playwright-snapshot==1.0; extra == "tests"
Requires-Dist: pytest-rerunfailures==12.0; extra == "tests"
Dynamic: author
Dynamic: author-email
Dynamic: description
Dynamic: description-content-type
Dynamic: license-file
Dynamic: provides-extra
Dynamic: requires-dist
Dynamic: requires-python
Dynamic: summary
